{"version": "https://jsonfeed.org/version/1", "title": "MARS", "home_page_url": "https://marstmu.com/", "feed_url": "https://marstmu.com/feed_json_created.json", "description": "MARS Website.", "icon": null, "authors": [{"name": "Zeul"}], "language": "en", "items": [{"id": "https://marstmu.com/blog/2024/01/29/updates-for-jan-29th/", "url": "https://marstmu.com/blog/2024/01/29/updates-for-jan-29th/", "title": "Updates for Jan 29th", "content_html": "<p>Trying to get the rss stuff working. Testing this</p>", "image": null, "date_published": "2024-01-29T00:00:00+00:00", "authors": [{"name": "zeul"}], "tags": []}, {"id": "https://marstmu.com/blog/2024/01/25/updates-for-jan-25th/", "url": "https://marstmu.com/blog/2024/01/25/updates-for-jan-25th/", "title": "Updates for Jan 25th", "content_html": "<p>The raspberry pis, the unifi stuff, and the allrockets.ca order has arrived. We will be giving out kits as soon as possible!</p>", "image": null, "date_published": "2024-01-25T00:00:00+00:00", "authors": [{"name": "zeul"}], "tags": []}, {"id": "https://marstmu.com/blog/2024/01/23/updates-for-jan-23rd/", "url": "https://marstmu.com/blog/2024/01/23/updates-for-jan-23rd/", "title": "Updates for Jan 23rd", "content_html": "<p>We have officially placed orders for everything in the BOM. We spent about $7000. We had an issue with ordering the starlink so Alessia will be ordering it t...</p>", "image": null, "date_published": "2024-01-23T00:00:00+00:00", "authors": [{"name": "zeul"}], "tags": []}, {"id": "https://marstmu.com/blog/2024/01/18/updates-for-jan-18th/", "url": "https://marstmu.com/blog/2024/01/18/updates-for-jan-18th/", "title": "Updates for Jan 18th", "content_html": "<p>Minor edits made to the website, including the addition/onboarding of a new helping hand for development and documentation (hi Mom!). More edits will be fort...</p>", "image": null, "date_published": "2024-01-18T00:00:00+00:00", "authors": [{"name": "Nate"}], "tags": []}, {"id": "https://marstmu.com/blog/2024/01/17/updates-for-jan-17th/", "url": "https://marstmu.com/blog/2024/01/17/updates-for-jan-17th/", "title": "Updates for Jan 17th", "content_html": "<p>More commits were made to the website today. I accepted a pull request from [ICARUS], who added their image to the teams section. The [tasks] section was upd...</p>", "image": null, "date_published": "2024-01-17T00:00:00+00:00", "authors": [{"name": "zeul"}], "tags": []}, {"id": "https://marstmu.com/blog/2024/01/16/site-updates/", "url": "https://marstmu.com/blog/2024/01/16/site-updates/", "title": "Site Updates", "content_html": "<p>We are really trying to push for a great website with as much helpful information as possible on it. This website will evolve over time, and we want to make ...</p>", "image": null, "date_published": "2024-01-16T00:00:00+00:00", "authors": [{"name": "zeul"}], "tags": []}, {"id": "https://marstmu.com/blog/2024/01/15/preliminary-design-review-pdr/", "url": "https://marstmu.com/blog/2024/01/15/preliminary-design-review-pdr/", "title": "Preliminary Design Review (PDR)", "content_html": "<p><img alt=\"team\" src=\"PDR1.JPG\">\nToday we successfully hosted the preliminary design reviews. Four out of the 9 currently registered teams showed up. There is one more on f...</p>", "image": null, "date_published": "2024-01-15T00:00:00+00:00", "authors": [{"name": "zeul"}], "tags": []}]}